run_ivette.py
ivette/__init__.py
ivette/classes.py
ivette/decorators.py
ivette/networking.py
ivette/processing.py
ivette/types.py
ivette/utils.py
ivette_client-0.2.15.data/data/ivette-client/config.json
ivette_client-0.2.15.dist-info/METADATA
ivette_client-0.2.15.dist-info/WHEEL
ivette_client-0.2.15.dist-info/entry_points.txt
ivette_client-0.2.15.dist-info/top_level.txt
ivette_client-0.2.15.dist-info/RECORD
