Metadata-Version: 2.1
Name: ivette-client
Version: 0.2.15
Summary: Python client for Ivette Computational chemistry and Bioinformatics project
Home-page: UNKNOWN
Author: Eduardo Bogado
License: Proprietary
Platform: UNKNOWN
